proalgotrader_protocols/__init__.py
proalgotrader_protocols/algorithm.py
proalgotrader_protocols/broker.py
proalgotrader_protocols/broker_manager.py
proalgotrader_protocols/chart.py
proalgotrader_protocols/data.py
proalgotrader_protocols/data_manager.py
proalgotrader_protocols/feed.py
proalgotrader_protocols/indicator.py
proalgotrader_protocols/store.py
proalgotrader_protocols/strategy.py
proalgotrader_protocols/symbol.py
proalgotrader_protocols/enums/__init__.py
proalgotrader_protocols/enums/account_type.py
proalgotrader_protocols/enums/market_type.py
proalgotrader_protocols/enums/order_type.py
proalgotrader_protocols/enums/position_type.py
proalgotrader_protocols/enums/product_type.py
proalgotrader_protocols/enums/segment_type.py
proalgotrader_protocols-0.0.4.dist-info/LICENSE
proalgotrader_protocols-0.0.4.dist-info/METADATA
proalgotrader_protocols-0.0.4.dist-info/WHEEL
proalgotrader_protocols-0.0.4.dist-info/top_level.txt
proalgotrader_protocols-0.0.4.dist-info/RECORD
