Metadata-Version: 2.1
Name: proalgotrader-protocols
Version: 0.0.4
Summary: ProAlgoTrader Protocols
Home-page: https://github.com/krunaldodiya/proalgotrader_protocols
Author: Krunal Dodiya
Author-email: kunal.dodiya1@gmail.com
Classifier: Programming Language :: Python :: 3
Classifier: Operating System :: OS Independent
License-File: LICENSE
Requires-Dist: requests
